scourgify/__init__.py
scourgify/address_constants.py
scourgify/cleaning.py
scourgify/exceptions.py
scourgify/normalize.py
scourgify/validations.py
scourgify/tests/__init__.py
scourgify/tests/test_address_normalization.py
scourgify/tests/test_cleaning.py
scourgify/tests/config/__init__.py
usaddress_scourgify-0.6.0.dist-info/LICENSE
usaddress_scourgify-0.6.0.dist-info/METADATA
usaddress_scourgify-0.6.0.dist-info/WHEEL
usaddress_scourgify-0.6.0.dist-info/top_level.txt
usaddress_scourgify-0.6.0.dist-info/RECORD
